dbconfigmanager/__init__.py
dbconfigmanager/client.py
dbconfigmanager/loader.py
dbconfigmanager-1.1.0.dist-info/licenses/LICENSE
dbconfigmanager-1.1.0.dist-info/METADATA
dbconfigmanager-1.1.0.dist-info/WHEEL
dbconfigmanager-1.1.0.dist-info/top_level.txt
dbconfigmanager-1.1.0.dist-info/RECORD
