Metadata-Version: 2.4
Name: dbconfigmanager
Version: 1.1.0
Summary: Load service environment variables from .env, cache, or remote API with full configurability
Author-email: Saadullah <saadullah.butt@caregenix.solutions>
License: MIT
Keywords: config,env,settings,service,dotenv
Classifier: Programming Language :: Python :: 3
Classifier: Programming Language :: Python :: 3.8
Classifier: License :: OSI Approved :: MIT License
Classifier: Operating System :: OS Independent
Requires-Python: >=3.8
License-File: LICENSE
Requires-Dist: python-dotenv>=1.0.0
Requires-Dist: requests>=2.28.0
Dynamic: license-file
